DESCRIPTION
MANIFEST.in
README
README.rst
setup.py
hex_storage/__init__.py
hex_storage/redsolution_setup/__init__.py
hex_storage/redsolution_setup/make.py
hex_storage/redsolution_setup/templates/hex_storage/redsolutioncms/settings.pyt
pinyin/__init__.py
pinyin/maps.py
pinyin/tests.py
pinyin/urlify.py
redsolutioncms.django_hex_storage.egg-info/PKG-INFO
redsolutioncms.django_hex_storage.egg-info/SOURCES.txt
redsolutioncms.django_hex_storage.egg-info/dependency_links.txt
redsolutioncms.django_hex_storage.egg-info/entry_points.txt
redsolutioncms.django_hex_storage.egg-info/not-zip-safe
redsolutioncms.django_hex_storage.egg-info/top_level.txt