Metadata-Version: 1.0
Name: redsolutioncms.django-hex-storage
Version: 0.1.2
Summary: Django hex storage is add-on on the top of Django file system.
Home-page: UNKNOWN
Author: Alexander Ivanov
Author-email: alexander.ivanov@redsolution.ru
License: GPLv3
Keywords: django file system storage
Platform: UNKNOWN
Classifier: Development Status :: 3 - Alpha
Classifier: Intended Audience :: Developers
Classifier: License :: OSI Approved :: GNU General Public License (GPL)
Classifier: Framework :: Django
Classifier: Environment :: Web Environment
Classifier: Natural Language :: Russian
Classifier: Natural Language :: English
Classifier: Operating System :: OS Independent
Classifier: Programming Language :: Python
Classifier: Topic :: Internet :: WWW/HTTP :: Site Management
